jajapy/__init__.py
jajapy/base/BW.py
jajapy/base/Base_HMM.py
jajapy/base/Base_MC.py
jajapy/base/Model.py
jajapy/base/Parametric_Model.py
jajapy/base/Set.py
jajapy/base/__init__.py
jajapy/base/tools.py
jajapy/ctmc/CTMC.py
jajapy/ctmc/__init__.py
jajapy/gohmm/GoHMM.py
jajapy/gohmm/__init__.py
jajapy/hmm/HMM.py
jajapy/hmm/__init__.py
jajapy/mc/Alergia.py
jajapy/mc/MC.py
jajapy/mc/__init__.py
jajapy/mdp/Active_BW_MDP.py
jajapy/mdp/IOAlergia.py
jajapy/mdp/MDP.py
jajapy/mdp/Scheduler.py
jajapy/mdp/__init__.py
jajapy/pctmc/PCTMC.py
jajapy/pctmc/__init__.py
jajapy/tests/CTMC_test.py
jajapy/tests/GoHMM_test.py
jajapy/tests/HMM_test.py
jajapy/tests/MC_test.py
jajapy/tests/MDP_test.py
jajapy/tests/PCTMC_test.py
jajapy/tests/__init__.py
jajapy/tests/model_converter_test.py
jajapy/tests/tools_test.py
jajapy/with_stormpy/__init__.py
jajapy/with_stormpy/model_converter.py
jajapy-0.10.8.dist-info/LICENSE
jajapy-0.10.8.dist-info/METADATA
jajapy-0.10.8.dist-info/WHEEL
jajapy-0.10.8.dist-info/top_level.txt
jajapy-0.10.8.dist-info/RECORD
