Metadata-Version: 2.1
Name: jajapy
Version: 0.10.8
Summary: Baum-Welch for all kind of Markov model
Home-page: UNKNOWN
Author: Raphaël Reynouard
Author-email: raphal20@ru.is
License: MIT
Platform: UNKNOWN
Classifier: Intended Audience :: Developers
Classifier: License :: OSI Approved :: MIT License
Classifier: Programming Language :: Python
Classifier: Programming Language :: Python :: 3
Classifier: Programming Language :: Python :: 3.6
Classifier: Programming Language :: Python :: 3.7
Classifier: Programming Language :: Python :: 3.8
Classifier: Programming Language :: Python :: 3.9
Classifier: Programming Language :: Python :: 3.10
Classifier: Operating System :: OS Independent
License-File: LICENSE
Requires-Dist: alive-progress
Requires-Dist: numpy
Requires-Dist: scipy
Requires-Dist: sympy
